Metadata-Version: 2.1
Name: signxml-references-modified
Version: 1.0.0
Summary: Python XML Signature and XAdES library
Home-page: https://github.com/deisymo/signxml
Author: Andrey Kislyuk
Author-email: kislyuk@gmail.com
License: Apache Software License
Platform: MacOS X
Platform: Posix
Classifier: Intended Audience :: Developers
Classifier: License :: OSI Approved :: Apache Software License
Classifier: Operating System :: MacOS :: MacOS X
Classifier: Operating System :: POSIX
Classifier: Programming Language :: Python
Classifier: Programming Language :: Python :: 3.7
Classifier: Programming Language :: Python :: 3.8
Classifier: Programming Language :: Python :: 3.9
Classifier: Programming Language :: Python :: 3.10
Classifier: Programming Language :: Python :: 3.11
Classifier: Programming Language :: Python :: 3.12
Classifier: Topic :: Software Development :: Libraries :: Python Modules
Requires-Python: >=3.7
License-File: LICENSE
License-File: NOTICE
Requires-Dist: certifi (>=2023.11.17)
Requires-Dist: cryptography (>=43)
Requires-Dist: lxml (<6,>=5.2.1)
Provides-Extra: tests
Requires-Dist: build ; extra == 'tests'
Requires-Dist: coverage ; extra == 'tests'
Requires-Dist: lxml-stubs ; extra == 'tests'
Requires-Dist: mypy ; extra == 'tests'
Requires-Dist: ruff ; extra == 'tests'
Requires-Dist: wheel ; extra == 'tests'
